Metadata-Version: 2.1
Name: constrained-sampler-maffettone
Version: 0.0.2
Summary: Package to generate numbers in the unit hypercube subject to constraints.
Home-page: https://github.com/maffettone/constrained_sampler
License: UNKNOWN
Platform: UNKNOWN
Classifier: Programming Language :: Python :: 3
Classifier: License :: OSI Approved :: MIT License
Classifier: Operating System :: OS Independent
Requires-Python: >=3.6
